{
  "ask_id": 0,
  "question": "What is the recommended tyre pressure for a mountain bike?",
  "answered": false,
  "verdict": "insufficient",
  "confidence": "low",
  "answer": "This question does not appear to be covered by the current corpus, so I will not answer it rather than risk inventing details. The most related records found are listed below.",
  "signals": {
    "question_ids": [],
    "named_known": [],
    "named_retrieved": [],
    "id_anchor": false,
    "n_terms": 5,
    "term_coverage": 0.2,
    "top_score": 0.03041,
    "n_strong": 8,
    "n_chunks": 8
  },
  "claims": [],
  "citations": [],
  "graph_paths": [],
  "sources": [
    {
      "rowid": 355,
      "artifact_id": "DOC-484",
      "source": "PLM",
      "art_kind": "document",
      "title": "K-200 Systems Acceptance Test Procedure",
      "prov_tier": 1,
      "tier_label": "formal",
      "chunk_idx": 0,
      "char_start": 0,
      "char_end": 350,
      "body": "DOC-484 | K-200 Systems Acceptance Test Procedure\n\n# K-200 Systems Acceptance Test Procedure\n\nDocument number: MD-DOC-484-A. Revision: A. Type: procedure. Author: Sam Dreher. Created: 2024-01-06. Last modified: 2024-03-15. Status: Released.\n\nThis document defines the requirements, interfaces, and verification approach for the Systems subsystem of the Kestrel K-200. Referenced parts: P-1089, P-1082.",
      "score": 0.030415,
      "legs": [
        "vector",
        "graph"
      ]
    },
    {
      "rowid": 779,
      "artifact_id": "REV-635",
      "source": "PLM",
      "art_kind": "document",
      "title": "Review of DOC-406: REV-635",
      "prov_tier": 1,
      "tier_label": "formal",
      "chunk_idx": 0,
      "char_start": 0,
      "char_end": 1001,
      "body": "REV-635 | Review of DOC-406: REV-635\n\n# Review Record REV-635\n\nDocument: DOC-406. Reviewer: Tyler Moss. Date: 2024-07-29. Overall disposition: Rejected.\n\n## Comments\n\n**C01** (Jordan Kim): Section 4.3: The specification should clarify the interface requirement for DOC-406. Recommend updating the acceptance criteria table. \u2014 *Action required*\n\n**C02** (Priya Nair): Section 6.2: The specification should clarify the interface requirement for DOC-406. Recommend updating the acceptance criteria table. \u2014 *Accepted*\n\n**C03** (Lena Okafor): Section 7.2: The specification should clarify the interface requirement for DOC-406. Recommend updating the acceptance criteria table. \u2014 *Accepted*\n\n**C04** (Felix Herrera): Section 2.4: The specification should clarify the interface requirement for DOC-406. Recommend updating the acceptance criteria table. \u2014 *Accepted*\n\n**C05** (Nina Schulz): Section 1.4: The specification should clarify the interface requirement for DOC-406. Recommend updating the acceptance criteria table. \u2014 *Action required*",
      "score": 0.029418,
      "legs": [
        "fts",
        "graph"
      ]
    },
    {
      "rowid": 332,
      "artifact_id": "DOC-462",
      "source": "PLM",
      "art_kind": "document",
      "title": "K-200 Sonar System Interface Control Document v2.0",
      "prov_tier": 1,
      "tier_label": "formal",
      "chunk_idx": 0,
      "char_start": 0,
      "char_end": 1129,
      "body": "DOC-462 | K-200 Sonar System Interface Control Document v2.0\n\n# K-200 Sonar System Interface Control Document\n\nDocument number: MD-DOC-462-B. Revision: B. Type: ICD. Author: Cass Doyle. Created: 2023-08-01. Last modified: 2024-10-15. Status: Released.\n\n## Change History\n- Rev A: Initial sonar ICD for DepthWave transducer (2023-08-01)\n- Rev B: Updated for AquaSound Corp transducer (P-1148 Rev B) per ECN-315 / ECR-218 (2024-10-15)\n\n## \u00a72 Transducer \u2014 P-1148 Rev B (AquaSound Corp)\n\nSupplier: AquaSound Corp. Frequency range: 100\u2013400kHz broadband. Centre frequency: 200kHz. Frequency stability: \u00b11.5kHz over operating temperature (-10\u00b0C to +50\u00b0C). Depth rating: 30m. Connector: IP68 Subconn circular. DNV-GL certified.\n\nThe original DepthWave supplier was replaced after KES-158 (frequency drift bug) documented 16kHz drift over thermal soak. Vendor selection rationale: WIKI-045 (Sonar Vendor Selection Meeting, 2024-08-29). Change authority: ECN-315.\n\n## \u00a76 Sonar Mounting\n\n### \u00a76.1 Mounting Bracket\n\nSonar transducer P-1148 is mounted on bracket P-1149 (Sonar Mounting Bracket, aluminium 6061-T6). See DRW-517 for full mounting drawing.\n\n### \u00a76.2 Cant Angle \u2014 Critical Design Parameter",
      "score": 0.028665,
      "legs": [
        "vector",
        "graph"
      ]
    },
    {
      "rowid": 226,
      "artifact_id": "ECR-229",
      "source": "PLM",
      "art_kind": "document",
      "title": "Comms datalink encryption upgrade: AES-256-GCM via P-1127 FPGA, radio P-1125\u2192P-1126",
      "prov_tier": 1,
      "tier_label": "formal",
      "chunk_idx": 0,
      "char_start": 0,
      "char_end": 1391,
      "body": "ECR-229 | Comms datalink encryption upgrade: AES-256-GCM via P-1127 FPGA, radio P-1125\u2192P-1126\n\nEngineering Change Request ECR-229.\n\nRaised by: Priya Nair (Comms/Datalink Engineer), 2025-01-29.\nStatus: Approved. Approved by: Felix Herrera (Systems Integration), 2025-02-05.\n\nSummary: Add AES-256-GCM hardware encryption module (P-1127 FPGA) to the datalink, and upgrade the radio from P-1125 (FreeWave 500kbps) to P-1126 (FreeWave 2Mbps dual-band) to accommodate the bandwidth overhead.\n\nRationale: A penetration test conducted in December 2024 (report MD-SEC-2024-11) found that the K-200 command and telemetry link was vulnerable to command injection \u2014 an attacker with a compatible FreeWave radio could inject spoofed command packets. The customer's security addendum (contract KES-203) requires AES-256-GCM end-to-end encryption on all command and telemetry traffic by programme milestone M4 (March 2025). This was agreed at WIKI-071 (Comms Encryption Upgrade Review, 2025-01-22).\n\nArchitecture (from WIKI-071): The P-1127 FPGA module (Lattice iCE40, implementing AES-256-GCM in hardware) sits between the datalink controller (P-1121) and the radio (P-1125/P-1126). Session keys are derived via ECDH on each power cycle, with key rotation every 60 minutes. The AES-256-GCM 16-byte auth tag and protocol overhead add approximately 3% throughput overhead. At 500kbps (P-1125) this is marginal; the P-1126 at 2Mbps provides sufficient headroom for full telemetry at 200ms update rate.",
      "score": 0.02481,
      "legs": [
        "vector",
        "graph"
      ]
    },
    {
      "rowid": 342,
      "artifact_id": "DOC-471",
      "source": "PLM",
      "art_kind": "document",
      "title": "K-200 Comms System Interface Control Document v3.0 (Rev C)",
      "prov_tier": 1,
      "tier_label": "formal",
      "chunk_idx": 0,
      "char_start": 0,
      "char_end": 1448,
      "body": "DOC-471 | K-200 Comms System Interface Control Document v3.0 (Rev C)\n\n# K-200 Comms System Interface Control Document\n\nDocument number: MD-DOC-471-C. Revision: C. Type: ICD. Author: Priya Nair. Created: 2023-06-01. Last modified: 2025-02-28. Status: Released.\n\n## Change History\n- Rev A: 900MHz FHSS baseline, P-1125 (2023-06-01)\n- Rev B: Diversity antenna system added (2024-03-01)\n- Rev C: AES-256-GCM encryption layer added, radio P-1125\u2192P-1126, P-1127 FPGA module (2025-02-28, per ECN-322)\n\n## \u00a73 Radio Subsystem \u2014 P-1126 Enhanced\n\nCurrent radio: FreeWave Enhanced Dual-Band (P-1126 Rev B). Frequency: 900MHz / 2.4GHz FHSS. Data rate: 2Mbps. Output power: 1W. Range: 15km at 1W. The P-1126 replaced P-1125 (500kbps) to accommodate the bandwidth overhead of AES-256-GCM encryption. Change authority: ECN-322.\n\n## \u00a74 Encryption \u2014 P-1127 FPGA Module\n\nAll command and telemetry traffic is encrypted with AES-256-GCM before transmission by the P-1127 FPGA encryption module (Lattice iCE40, hardware implementation). The FPGA module sits between the datalink controller (P-1121) and the radio (P-1126). Session keys are derived via ECDH on power-cycle, with 60-minute rotation. Implementation: SRC-018 (encryption_handler.c). GCS protocol stack: SRC-024 (gcs_ui_backend.py).\n\nSecurity requirement source: Customer contract security addendum, KES-203, penetration test MD-SEC-2024-11. Design review: WIKI-071.\n\n## \u00a75 Protocol \u2014 see DOC-472\n\nDetailed protocol specification in DOC-472 (Comms Protocol Specification Rev B).",
      "score": 0.024448,
      "legs": [
        "vector",
        "graph"
      ]
    },
    {
      "rowid": 103,
      "artifact_id": "P-1089",
      "source": "PLM",
      "art_kind": "entity",
      "title": "Pressure Relief Valve",
      "prov_tier": 1,
      "tier_label": "formal",
      "chunk_idx": 0,
      "char_start": 0,
      "char_end": 150,
      "body": "P-1089 | Pressure Relief Valve\n\nPressure Relief Valve. Subsystem: Battery. Material: spring-loaded, 1.5 bar, IP67. Mass: 9g. Manufactured by ReliefsRUS. Revision A. Part class: COTS.",
      "score": 0.016393,
      "legs": [
        "fts"
      ]
    },
    {
      "rowid": 275,
      "artifact_id": "DOC-406",
      "source": "PLM",
      "art_kind": "document",
      "title": "K-200 Propulsion Maintenance Procedure",
      "prov_tier": 1,
      "tier_label": "formal",
      "chunk_idx": 0,
      "char_start": 0,
      "char_end": 342,
      "body": "DOC-406 | K-200 Propulsion Maintenance Procedure\n\n# K-200 Propulsion Maintenance Procedure\n\nDocument number: MD-DOC-406-A. Revision: A. Type: manual. Author: Nina Schulz. Created: 2024-11-15. Last modified: 2025-01-27. Status: Released.\n\nThis document defines the requirements, interfaces, and verification approach for the Propulsion subsystem of the Kestrel K-200. Referenced parts: P-1064.",
      "score": 0.016393,
      "legs": [
        "vector"
      ]
    },
    {
      "rowid": 75,
      "artifact_id": "P-1061",
      "source": "PLM",
      "art_kind": "entity",
      "title": "Battery Enclosure",
      "prov_tier": 1,
      "tier_label": "formal",
      "chunk_idx": 0,
      "char_start": 0,
      "char_end": 152,
      "body": "P-1061 | Battery Enclosure\n\nBattery Enclosure. Subsystem: Battery. Material: aluminium 6061-T6, IP67. Mass: 310g. Manufactured by Meridian Dynamics. Revision B. Part class: custom.",
      "score": 0.016393,
      "legs": [
        "graph"
      ]
    }
  ],
  "latency_ms": 4,
  "backend": "mock/mock",
  "retrieval": {
    "exact_hits": 0,
    "fts_hits": 20,
    "vector_hits": 20,
    "graph_hits": 38,
    "anchors": [
      "P-1089",
      "DOC-406",
      "REV-629",
      "WIKI-045",
      "REV-632",
      "WIKI-071"
    ],
    "fused_candidates": 73
  }
}